{
  "timestamp": "2026-05-01T19:00:25.673211+00:00",
  "sentiment": "slightly_bearish",
  "score": -0.48,
  "fear_greed": {
    "value": 26,
    "label": "Fear",
    "trend": "falling"
  },
  "key_events": [
    "Tether posts $1.04 billion Q1 profit, reaches $8.23 billion reserve buffer",
    "SBI Holdings eyes stake in crypto exchange Bitbank to build digital asset powerhouse",
    "DeFi can freeze stolen funds, but not everyone agrees it should",
    "Ethereum Foundation finalizes sale of 10,000 ether to BitMine as part of its treasury strategy",
    "Canadian pension giant AIMCo buys the dip in Strategy, now sitting on $69 million unrealized gain"
  ],
  "affected_assets": [
    "BTC",
    "ETH",
    "SOL",
    "DOGE",
    "OP"
  ],
  "trending_coins": [
    "PENGU",
    "MEGA",
    "ACN",
    "UB",
    "HYPE",
    "BTC",
    "ETH"
  ],
  "risk_level": "HIGH",
  "vasily_action": "REDUCE_SIZE — уменьши размер новых позиций на 50%, ужесточи SL",
  "news_count": 20,
  "hacks_detected": 0,
  "fetch_time_sec": 2.84,
  "cached_at": 1777662025.6734731
}